{
  "reader": "Mistral-Small-4-119B",
  "dataset": "HotpotQA",
  "n_training_questions": 200,
  "feature_names": [
    "confidence",
    "ans_len",
    "bridge_cues",
    "score_gap",
    "score_top1",
    "qtype"
  ],
  "qtype_map": {
    "entity": 0,
    "date": 1,
    "yes_no": 2,
    "count": 3,
    "other": 4
  },
  "raser2": {
    "threshold_theta": 0.2,
    "bridgeable_label_tau": 0.1,
    "n_bridgeable_positives": 17,
    "bridgeable_rate": 0.085
  },
  "raser3": {
    "cost_budget_fraction": 0.6,
    "deployed_lambda": 5e-05,
    "training_route_costs": {
      "STOP": 1290.14,
      "PRUNE": 3413.375,
      "ITER": 3436.86
    },
    "training_route_f1": {
      "STOP": 0.6991893988364576,
      "PRUNE": 0.7160838932309521,
      "ITER": 0.7728975975005387
    }
  },
  "gbm_hyperparameters": {
    "n_estimators": 100,
    "max_depth": 3,
    "learning_rate": 0.1,
    "subsample": 0.8,
    "random_state": 42
  }
}